Adafruit_ILI9341/ILI9341.py
Adafruit_ILI9341/__init__.py
Adafruit_ILI9341-1.5.1.dist-info/metadata.json
Adafruit_ILI9341-1.5.1.dist-info/METADATA
Adafruit_ILI9341-1.5.1.dist-info/RECORD
Adafruit_ILI9341-1.5.1.dist-info/WHEEL
Adafruit_ILI9341-1.5.1.dist-info/DESCRIPTION.rst
Adafruit_ILI9341-1.5.1.dist-info/dependency_links.txt
Adafruit_ILI9341-1.5.1.dist-info/top_level.txt
